{
  "db_name": "PostgreSQL",
  "query": "\n        SELECT \n            COALESCE(SUM(\n                (t.amount - COALESCE(t.transaction_sponsorship_fee, 0)) * \n                (CAST($1 AS DECIMAL) / 100.0)\n            ), 0) as platform_fees\n        FROM transactions t\n        WHERE t.created_at BETWEEN $2 AND $3\n        AND t.status = 'completed'\n        AND t.currency = 'USDC'\n        ",
  "describe": {
    "columns": [
      {
        "ordinal": 0,
        "name": "platform_fees",
        "type_info": "Numeric"
      }
    ],
    "parameters": {
      "Left": [
        "Numeric",
        "Timestamptz",
        "Timestamptz"
      ]
    },
    "nullable": [
      null
    ]
  },
  "hash": "2b2026ddf1d5f0168fba124a064b9925c322c0512a740439474b077547d888c1"
}
